==== Main Info ====

Version:		52.0 (Major.Minor) [jdk version 1.8]
Constant pool count:	34
Access flags:		0x0021 [super, public]
This class:		cp index #6 <HelloWorld>
Super class:		cp index #7 <java/lang/Object>
Interfaces count:	0
Fields count:		1
Methods count:		3
Attributes count:	1

==== Constant Pool ====

[1]: CONST_Methodref (tag = 10)
	Class name: #7 <java/lang/Object>
	Name and type: #19 <java/lang/Object : ()V>

[2]: CONST_Fieldref (tag = 9)
	Class name: #20 <java/lang/System>
	Name and type: #21 <java/lang/System : Ljava/io/PrintStream;>

[3]: CONST_Fieldref (tag = 9)
	Class name: #6 <HelloWorld>
	Name and type: #22 <HelloWorld : Ljava/lang/String;>

[4]: CONST_Methodref (tag = 10)
	Class name: #23 <java/io/PrintStream>
	Name and type: #24 <java/io/PrintStream : (Ljava/lang/String;)V>

[5]: CONST_String (tag = 8)
	String: #25 Hello World!

[6]: CONST_Class (tag = 7)
	Class name: #26 <HelloWorld>

[7]: CONST_Class (tag = 7)
	Class name: #27 <java/lang/Object>

[8]: CONST_Utf8 (tag = 1)
	Length of byte array: 3
	Length of string: 3
	String: str

[9]: CONST_Utf8 (tag = 1)
	Length of byte array: 18
	Length of string: 18
	String: Ljava/lang/String;

[10]: CONST_Utf8 (tag = 1)
	Length of byte array: 6
	Length of string: 6
	String: <init>

[11]: CONST_Utf8 (tag = 1)
	Length of byte array: 3
	Length of string: 3
	String: ()V

[12]: CONST_Utf8 (tag = 1)
	Length of byte array: 4
	Length of string: 4
	String: Code

[13]: CONST_Utf8 (tag = 1)
	Length of byte array: 15
	Length of string: 15
	String: LineNumberTable

[14]: CONST_Utf8 (tag = 1)
	Length of byte array: 4
	Length of string: 4
	String: main

[15]: CONST_Utf8 (tag = 1)
	Length of byte array: 22
	Length of string: 22
	String: ([Ljava/lang/String;)V

[16]: CONST_Utf8 (tag = 1)
	Length of byte array: 8
	Length of string: 8
	String: <clinit>

[17]: CONST_Utf8 (tag = 1)
	Length of byte array: 10
	Length of string: 10
	String: SourceFile

[18]: CONST_Utf8 (tag = 1)
	Length of byte array: 15
	Length of string: 15
	String: HelloWorld.java

[19]: CONST_NameAndType (tag = 12)
	Name: #10 <<init>>
	Descriptor: #11 <()V>

[20]: CONST_Class (tag = 7)
	Class name: #28 <java/lang/System>

[21]: CONST_NameAndType (tag = 12)
	Name: #29 <out>
	Descriptor: #30 <Ljava/io/PrintStream;>

[22]: CONST_NameAndType (tag = 12)
	Name: #8 <str>
	Descriptor: #9 <Ljava/lang/String;>

[23]: CONST_Class (tag = 7)
	Class name: #31 <java/io/PrintStream>

[24]: CONST_NameAndType (tag = 12)
	Name: #32 <println>
	Descriptor: #33 <(Ljava/lang/String;)V>

[25]: CONST_Utf8 (tag = 1)
	Length of byte array: 12
	Length of string: 12
	String: Hello World!

[26]: CONST_Utf8 (tag = 1)
	Length of byte array: 10
	Length of string: 10
	String: HelloWorld

[27]: CONST_Utf8 (tag = 1)
	Length of byte array: 16
	Length of string: 16
	String: java/lang/Object

[28]: CONST_Utf8 (tag = 1)
	Length of byte array: 16
	Length of string: 16
	String: java/lang/System

[29]: CONST_Utf8 (tag = 1)
	Length of byte array: 3
	Length of string: 3
	String: out

[30]: CONST_Utf8 (tag = 1)
	Length of byte array: 21
	Length of string: 21
	String: Ljava/io/PrintStream;

[31]: CONST_Utf8 (tag = 1)
	Length of byte array: 19
	Length of string: 19
	String: java/io/PrintStream

[32]: CONST_Utf8 (tag = 1)
	Length of byte array: 7
	Length of string: 7
	String: println

[33]: CONST_Utf8 (tag = 1)
	Length of byte array: 21
	Length of string: 21
	String: (Ljava/lang/String;)V

==== Fields ====

	Field #1:

		name_index:       #8 <str>
		descriptor_index: #9 <Ljava/lang/String;>
		access_flags:     0x000A [private, static]
		attr_count: 0


==== Methods ====

Method #1:

	name_index:        #10 <<init>>
	descriptor_index:  #11 <()V>
	access_flags:      0x0001 [public]
	attribute_count:   1

	Method Attribute #1 - Code:

max_stack: 1, max_locals: 1, code_length: 5
exception_table_length: 0, attribute_count: 1

Bytecode:
Offset	Mnemonic	Parameters
0	aload_0
1	invokespecial	#1 <Method java/lang/Object.<init>, descriptor: ()V>
4	return

Code Attribute #1 - LineNumberTable:

line_number_table_length: 1

Table:	index	line_number	start_pc
	1	1		0


Method #2:

	name_index:        #14 <main>
	descriptor_index:  #15 <([Ljava/lang/String;)V>
	access_flags:      0x0009 [public, static]
	attribute_count:   1

	Method Attribute #1 - Code:

max_stack: 2, max_locals: 1, code_length: 10
exception_table_length: 0, attribute_count: 1

Bytecode:
Offset	Mnemonic	Parameters
0	getstatic	#2 <Field java/lang/System.out, descriptor: Ljava/io/PrintStream;>
3	getstatic	#3 <Field HelloWorld.str, descriptor: Ljava/lang/String;>
6	invokevirtual	#4 <Method java/io/PrintStream.println, descriptor: (Ljava/lang/String;)V>
9	return

Code Attribute #1 - LineNumberTable:

line_number_table_length: 2

Table:	index	line_number	start_pc
	1	6		0
	2	7		9


Method #3:

	name_index:        #16 <<clinit>>
	descriptor_index:  #11 <()V>
	access_flags:      0x0008 [static]
	attribute_count:   1

	Method Attribute #1 - Code:

max_stack: 1, max_locals: 0, code_length: 6
exception_table_length: 0, attribute_count: 1

Bytecode:
Offset	Mnemonic	Parameters
0	ldc		#5 (string: "Hello World!")
2	putstatic	#3 <Field HelloWorld.str, descriptor: Ljava/lang/String;>
5	return

Code Attribute #1 - LineNumberTable:

line_number_table_length: 1

Table:	index	line_number	start_pc
	1	3		0


==== Class Attributes ====

	Attribute #1 - SourceFile:

sourcefile_index: #18 <HelloWorld.java>
