==== Main Info ====

Version:		52.0 (Major.Minor) [jdk version 1.8]
Constant pool count:	121
Access flags:		0x0021 [super, public]
This class:		cp index #43 <examples/LongCode>
Super class:		cp index #44 <java/lang/Object>
Interfaces count:	2
Fields count:		6
Methods count:		5
Attributes count:	2

==== Constant Pool ====

[1]: CONST_Methodref (tag = 10)
	Class name: #44 <java/lang/Object>
	Name and type: #84 <java/lang/Object : ()V>

[2]: CONST_Class (tag = 7)
	Class name: #85 <[[I>

[3]: CONST_Class (tag = 7)
	Class name: #52 <[I>

[4]: CONST_Fieldref (tag = 9)
	Class name: #43 <examples/LongCode>
	Name and type: #86 <examples/LongCode : [[[I>

[5]: CONST_Class (tag = 7)
	Class name: #87 <[D>

[6]: CONST_Double (tag = 6)
	High bytes:   0x405EDD2F
	Low  bytes:   0x1A9FBE77
	Double: 1.234560e+02

[8]: CONST_Double (tag = 6)
	High bytes:   0xC0847291
	Low  bytes:   0x6872B021
	Double: -6.543210e+02

[10]: CONST_Double (tag = 6)
	High bytes:   0x41CD6F34
	Low  bytes:   0x588FCD6F
	Double: 9.876543e+08

[12]: CONST_Class (tag = 7)
	Class name: #88 <java/lang/Double>

[13]: CONST_Double (tag = 6)
	High bytes:   0x7FEFFFFF
	Low  bytes:   0xFFFFFFFF
	Double: 1.797693e+308

[15]: CONST_Double (tag = 6)
	High bytes:   0x00000000
	Low  bytes:   0x00000001
	Double: 4.940656e-324

[17]: CONST_Double (tag = 6)
	High bytes:   0x00100000
	Low  bytes:   0x00000000
	Double: 2.225074e-308

[19]: CONST_Double (tag = 6)
	High bytes:   0x7FF80000
	Low  bytes:   0x00000000
	Double: nan

[21]: CONST_Double (tag = 6)
	High bytes:   0x7FF00000
	Low  bytes:   0x00000000
	Double: inf

[23]: CONST_Double (tag = 6)
	High bytes:   0xFFF00000
	Low  bytes:   0x00000000
	Double: -inf

[25]: CONST_Fieldref (tag = 9)
	Class name: #43 <examples/LongCode>
	Name and type: #89 <examples/LongCode : [[D>

[26]: CONST_Class (tag = 7)
	Class name: #90 <examples/LongCode$NestedClass>

[27]: CONST_Methodref (tag = 10)
	Class name: #26 <examples/LongCode$NestedClass>
	Name and type: #91 <examples/LongCode$NestedClass : (Lexamples/LongCode;)V>

[28]: CONST_InterfaceMethodref (tag = 11)
	Class name: #49 <examples/LongCode$Test>
	Name and type: #92 <examples/LongCode$Test : ([I)I>

[29]: CONST_Fieldref (tag = 9)
	Class name: #43 <examples/LongCode>
	Name and type: #93 <examples/LongCode : J>

[30]: CONST_Float (tag = 4)
	Bytes: 0x41A00000
	Float: 2.000000e+01

[31]: CONST_Class (tag = 7)
	Class name: #94 <java/lang/Error>

[32]: CONST_Methodref (tag = 10)
	Class name: #31 <java/lang/Error>
	Name and type: #84 <java/lang/Error : ()V>

[33]: CONST_String (tag = 8)
	String: #95 ola

[34]: CONST_Class (tag = 7)
	Class name: #96 <java/lang/String>

[35]: CONST_Fieldref (tag = 9)
	Class name: #97 <java/lang/System>
	Name and type: #98 <java/lang/System : Ljava/io/PrintStream;>

[36]: CONST_Methodref (tag = 10)
	Class name: #99 <java/io/PrintStream>
	Name and type: #100 <java/io/PrintStream : (Ljava/lang/String;)V>

[37]: CONST_Class (tag = 7)
	Class name: #101 <[[Ljava/lang/String;>

[38]: CONST_Class (tag = 7)
	Class name: #102 <java/lang/ArithmeticException>

[39]: CONST_Methodref (tag = 10)
	Class name: #99 <java/io/PrintStream>
	Name and type: #103 <java/io/PrintStream : (Ljava/lang/Object;)V>

[40]: CONST_Fieldref (tag = 9)
	Class name: #43 <examples/LongCode>
	Name and type: #104 <examples/LongCode : [I>

[41]: CONST_Long (tag = 5)
	High bytes: 0x015EE2A3
	Low  bytes: 0x21CE7D15
	Long: 98765432123456789

[43]: CONST_Class (tag = 7)
	Class name: #105 <examples/LongCode>

[44]: CONST_Class (tag = 7)
	Class name: #106 <java/lang/Object>

[45]: CONST_Class (tag = 7)
	Class name: #107 <java/util/EventListener>

[46]: CONST_Class (tag = 7)
	Class name: #108 <java/util/RandomAccess>

[47]: CONST_Utf8 (tag = 1)
	Length of byte array: 11
	Length of string: 11
	String: NestedClass

[48]: CONST_Utf8 (tag = 1)
	Length of byte array: 12
	Length of string: 12
	String: InnerClasses

[49]: CONST_Class (tag = 7)
	Class name: #109 <examples/LongCode$Test>

[50]: CONST_Utf8 (tag = 1)
	Length of byte array: 4
	Length of string: 4
	String: Test

[51]: CONST_Utf8 (tag = 1)
	Length of byte array: 12
	Length of string: 12
	String: array_member

[52]: CONST_Utf8 (tag = 1)
	Length of byte array: 2
	Length of string: 2
	String: [I

[53]: CONST_Utf8 (tag = 1)
	Length of byte array: 17
	Length of string: 17
	String: deprecated_member

[54]: CONST_Utf8 (tag = 1)
	Length of byte array: 1
	Length of string: 1
	String: F

[55]: CONST_Utf8 (tag = 1)
	Length of byte array: 10
	Length of string: 10
	String: Deprecated

[56]: CONST_Utf8 (tag = 1)
	Length of byte array: 25
	Length of string: 25
	String: RuntimeVisibleAnnotations

[57]: CONST_Utf8 (tag = 1)
	Length of byte array: 22
	Length of string: 22
	String: Ljava/lang/Deprecated;

[58]: CONST_Utf8 (tag = 1)
	Length of byte array: 18
	Length of string: 18
	String: static_long_member

[59]: CONST_Utf8 (tag = 1)
	Length of byte array: 1
	Length of string: 1
	String: J

[60]: CONST_Utf8 (tag = 1)
	Length of byte array: 12
	Length of string: 6
	String: ??????
	UTF-8 Characters: πφμβƒé

[61]: CONST_Utf8 (tag = 1)
	Length of byte array: 18
	Length of string: 18
	String: Ljava/lang/String;

[62]: CONST_Utf8 (tag = 1)
	Length of byte array: 8
	Length of string: 8
	String: matrix3d

[63]: CONST_Utf8 (tag = 1)
	Length of byte array: 4
	Length of string: 4
	String: [[[I

[64]: CONST_Utf8 (tag = 1)
	Length of byte array: 8
	Length of string: 8
	String: matrix2d

[65]: CONST_Utf8 (tag = 1)
	Length of byte array: 3
	Length of string: 3
	String: [[D

[66]: CONST_Utf8 (tag = 1)
	Length of byte array: 6
	Length of string: 6
	String: <init>

[67]: CONST_Utf8 (tag = 1)
	Length of byte array: 3
	Length of string: 3
	String: ()V

[68]: CONST_Utf8 (tag = 1)
	Length of byte array: 4
	Length of string: 4
	String: Code

[69]: CONST_Utf8 (tag = 1)
	Length of byte array: 15
	Length of string: 15
	String: LineNumberTable

[70]: CONST_Utf8 (tag = 1)
	Length of byte array: 8
	Length of string: 8
	String: mymethod

[71]: CONST_Utf8 (tag = 1)
	Length of byte array: 5
	Length of string: 5
	String: (IJ)V

[72]: CONST_Utf8 (tag = 1)
	Length of byte array: 5
	Length of string: 5
	String: arith

[73]: CONST_Utf8 (tag = 1)
	Length of byte array: 6
	Length of string: 6
	String: (IFB)J

[74]: CONST_Utf8 (tag = 1)
	Length of byte array: 13
	Length of string: 13
	String: StackMapTable

[75]: CONST_Utf8 (tag = 1)
	Length of byte array: 10
	Length of string: 10
	String: Exceptions

[76]: CONST_Utf8 (tag = 1)
	Length of byte array: 4
	Length of string: 4
	String: main

[77]: CONST_Utf8 (tag = 1)
	Length of byte array: 22
	Length of string: 22
	String: ([Ljava/lang/String;)V

[78]: CONST_Class (tag = 7)
	Class name: #106 <java/lang/Object>

[79]: CONST_Class (tag = 7)
	Class name: #110 <[Ljava/lang/String;>

[80]: CONST_Class (tag = 7)
	Class name: #102 <java/lang/ArithmeticException>

[81]: CONST_Utf8 (tag = 1)
	Length of byte array: 8
	Length of string: 8
	String: <clinit>

[82]: CONST_Utf8 (tag = 1)
	Length of byte array: 10
	Length of string: 10
	String: SourceFile

[83]: CONST_Utf8 (tag = 1)
	Length of byte array: 13
	Length of string: 13
	String: LongCode.java

[84]: CONST_NameAndType (tag = 12)
	Name: #66 <<init>>
	Descriptor: #67 <()V>

[85]: CONST_Utf8 (tag = 1)
	Length of byte array: 3
	Length of string: 3
	String: [[I

[86]: CONST_NameAndType (tag = 12)
	Name: #62 <matrix3d>
	Descriptor: #63 <[[[I>

[87]: CONST_Utf8 (tag = 1)
	Length of byte array: 2
	Length of string: 2
	String: [D

[88]: CONST_Utf8 (tag = 1)
	Length of byte array: 16
	Length of string: 16
	String: java/lang/Double

[89]: CONST_NameAndType (tag = 12)
	Name: #64 <matrix2d>
	Descriptor: #65 <[[D>

[90]: CONST_Utf8 (tag = 1)
	Length of byte array: 29
	Length of string: 29
	String: examples/LongCode$NestedClass

[91]: CONST_NameAndType (tag = 12)
	Name: #66 <<init>>
	Descriptor: #111 <(Lexamples/LongCode;)V>

[92]: CONST_NameAndType (tag = 12)
	Name: #112 <method1>
	Descriptor: #113 <([I)I>

[93]: CONST_NameAndType (tag = 12)
	Name: #58 <static_long_member>
	Descriptor: #59 <J>

[94]: CONST_Utf8 (tag = 1)
	Length of byte array: 15
	Length of string: 15
	String: java/lang/Error

[95]: CONST_Utf8 (tag = 1)
	Length of byte array: 3
	Length of string: 3
	String: ola

[96]: CONST_Utf8 (tag = 1)
	Length of byte array: 16
	Length of string: 16
	String: java/lang/String

[97]: CONST_Class (tag = 7)
	Class name: #114 <java/lang/System>

[98]: CONST_NameAndType (tag = 12)
	Name: #115 <out>
	Descriptor: #116 <Ljava/io/PrintStream;>

[99]: CONST_Class (tag = 7)
	Class name: #117 <java/io/PrintStream>

[100]: CONST_NameAndType (tag = 12)
	Name: #118 <println>
	Descriptor: #119 <(Ljava/lang/String;)V>

[101]: CONST_Utf8 (tag = 1)
	Length of byte array: 20
	Length of string: 20
	String: [[Ljava/lang/String;

[102]: CONST_Utf8 (tag = 1)
	Length of byte array: 29
	Length of string: 29
	String: java/lang/ArithmeticException

[103]: CONST_NameAndType (tag = 12)
	Name: #118 <println>
	Descriptor: #120 <(Ljava/lang/Object;)V>

[104]: CONST_NameAndType (tag = 12)
	Name: #51 <array_member>
	Descriptor: #52 <[I>

[105]: CONST_Utf8 (tag = 1)
	Length of byte array: 17
	Length of string: 17
	String: examples/LongCode

[106]: CONST_Utf8 (tag = 1)
	Length of byte array: 16
	Length of string: 16
	String: java/lang/Object

[107]: CONST_Utf8 (tag = 1)
	Length of byte array: 23
	Length of string: 23
	String: java/util/EventListener

[108]: CONST_Utf8 (tag = 1)
	Length of byte array: 22
	Length of string: 22
	String: java/util/RandomAccess

[109]: CONST_Utf8 (tag = 1)
	Length of byte array: 22
	Length of string: 22
	String: examples/LongCode$Test

[110]: CONST_Utf8 (tag = 1)
	Length of byte array: 19
	Length of string: 19
	String: [Ljava/lang/String;

[111]: CONST_Utf8 (tag = 1)
	Length of byte array: 22
	Length of string: 22
	String: (Lexamples/LongCode;)V

[112]: CONST_Utf8 (tag = 1)
	Length of byte array: 7
	Length of string: 7
	String: method1

[113]: CONST_Utf8 (tag = 1)
	Length of byte array: 5
	Length of string: 5
	String: ([I)I

[114]: CONST_Utf8 (tag = 1)
	Length of byte array: 16
	Length of string: 16
	String: java/lang/System

[115]: CONST_Utf8 (tag = 1)
	Length of byte array: 3
	Length of string: 3
	String: out

[116]: CONST_Utf8 (tag = 1)
	Length of byte array: 21
	Length of string: 21
	String: Ljava/io/PrintStream;

[117]: CONST_Utf8 (tag = 1)
	Length of byte array: 19
	Length of string: 19
	String: java/io/PrintStream

[118]: CONST_Utf8 (tag = 1)
	Length of byte array: 7
	Length of string: 7
	String: println

[119]: CONST_Utf8 (tag = 1)
	Length of byte array: 21
	Length of string: 21
	String: (Ljava/lang/String;)V

[120]: CONST_Utf8 (tag = 1)
	Length of byte array: 21
	Length of string: 21
	String: (Ljava/lang/Object;)V

==== Interfaces implemented by the class ====

	Interface #1: #45 <java/util/EventListener>
	Interface #2: #46 <java/util/RandomAccess>

==== Fields ====

	Field #1:

		name_index:       #51 <array_member>
		descriptor_index: #52 <[I>
		access_flags:     0x001A [private, static, final]
		attributes_count: 0


	Field #2:

		name_index:       #53 <deprecated_member>
		descriptor_index: #54 <F>
		access_flags:     0x0001 [public]
		attributes_count: 2

		Field Attribute #1 - Deprecated:
Attribute not implemented and ignored.

		Field Attribute #2 - RuntimeVisibleAnnotations:
Attribute not implemented and ignored.


	Field #3:

		name_index:       #58 <static_long_member>
		descriptor_index: #59 <J>
		access_flags:     0x0009 [public, static]
		attributes_count: 0


	Field #4:

		name_index:       #60 <??????>
		descriptor_index: #61 <Ljava/lang/String;>
		access_flags:     0x0002 [private]
		attributes_count: 0


	Field #5:

		name_index:       #62 <matrix3d>
		descriptor_index: #63 <[[[I>
		access_flags:     0x0002 [private]
		attributes_count: 0


	Field #6:

		name_index:       #64 <matrix2d>
		descriptor_index: #65 <[[D>
		access_flags:     0x0001 [public]
		attributes_count: 0


==== Methods ====

Method #1:

	name_index:        #66 <<init>>
	descriptor_index:  #67 <()V>
	access_flags:      0x0001 [public]
	attribute_count:   1

	Method Attribute #1 - Code:

max_stack: 11, max_locals: 1, code_length: 166
exception_table_length: 0, attribute_count: 1

Bytecode:
Offset	Mnemonic	Parameters
0	aload_0
1	invokespecial	#1 <Method java/lang/Object.<init>, descriptor: ()V>
4	aload_0
5	iconst_2
6	anewarray	#2 (class: [[I)
9	dup
10	iconst_0
11	iconst_2
12	anewarray	#3 (class: [I)
15	dup
16	iconst_0
17	iconst_2
18	newarray	10 (array of int)
20	dup
21	iconst_0
22	iconst_1
23	iastore
24	dup
25	iconst_1
26	iconst_2
27	iastore
28	aastore
29	dup
30	iconst_1
31	iconst_2
32	newarray	10 (array of int)
34	dup
35	iconst_0
36	iconst_3
37	iastore
38	dup
39	iconst_1
40	iconst_4
41	iastore
42	aastore
43	aastore
44	dup
45	iconst_1
46	iconst_2
47	anewarray	#3 (class: [I)
50	dup
51	iconst_0
52	iconst_2
53	newarray	10 (array of int)
55	dup
56	iconst_0
57	iconst_5
58	iastore
59	dup
60	iconst_1
61	bipush		6
63	iastore
64	aastore
65	dup
66	iconst_1
67	iconst_2
68	newarray	10 (array of int)
70	dup
71	iconst_0
72	bipush		7
74	iastore
75	dup
76	iconst_1
77	bipush		8
79	iastore
80	aastore
81	aastore
82	putfield	#4 <Field examples/LongCode.matrix3d, descriptor: [[[I>
85	aload_0
86	iconst_3
87	anewarray	#5 (class: [D)
90	dup
91	iconst_0
92	iconst_3
93	newarray	7 (array of double)
95	dup
96	iconst_0
97	ldc2_w		#6 (double: 1.234560e+02)
100	dastore
101	dup
102	iconst_1
103	ldc2_w		#8 (double: -6.543210e+02)
106	dastore
107	dup
108	iconst_2
109	ldc2_w		#10 (double: 9.876543e+08)
112	dastore
113	aastore
114	dup
115	iconst_1
116	iconst_3
117	newarray	7 (array of double)
119	dup
120	iconst_0
121	ldc2_w		#13 (double: 1.797693e+308)
124	dastore
125	dup
126	iconst_1
127	ldc2_w		#15 (double: 4.940656e-324)
130	dastore
131	dup
132	iconst_2
133	ldc2_w		#17 (double: 2.225074e-308)
136	dastore
137	aastore
138	dup
139	iconst_2
140	iconst_3
141	newarray	7 (array of double)
143	dup
144	iconst_0
145	ldc2_w		#19 (double: nan)
148	dastore
149	dup
150	iconst_1
151	ldc2_w		#21 (double: inf)
154	dastore
155	dup
156	iconst_2
157	ldc2_w		#23 (double: -inf)
160	dastore
161	aastore
162	putfield	#25 <Field examples/LongCode.matrix2d, descriptor: [[D>
165	return

Code Attribute #1 - LineNumberTable:

line_number_table_length: 3

Table:	index	line_number	start_pc
	1	5		0
	2	13		4
	3	20		85


Method #2:

	name_index:        #70 <mymethod>
	descriptor_index:  #71 <(IJ)V>
	access_flags:      0x0001 [public]
	attribute_count:   1

	Method Attribute #1 - Code:

max_stack: 4, max_locals: 6, code_length: 35
exception_table_length: 0, attribute_count: 1

Bytecode:
Offset	Mnemonic	Parameters
0	iconst_2
1	newarray	10 (array of int)
3	astore		4
5	new		#26 (class: examples/LongCode$NestedClass)
8	dup
9	aload_0
10	invokespecial	#27 <Method examples/LongCode$NestedClass.<init>, descriptor: (Lexamples/LongCode;)V>
13	astore		5
15	aload		4
17	iconst_0
18	aload		5
20	aload		4
22	invokeinterface	#28, count: 2 (InterfaceMethod examples/LongCode$Test.method1, descriptor: ([I)I)
27	iastore
28	lload_2
29	getstatic	#29 <Field examples/LongCode.static_long_member, descriptor: J>
32	ladd
33	lstore_2
34	return

Code Attribute #1 - LineNumberTable:

line_number_table_length: 5

Table:	index	line_number	start_pc
	1	37		0
	2	38		5
	3	39		15
	4	40		28
	5	41		34


Method #3:

	name_index:        #72 <arith>
	descriptor_index:  #73 <(IFB)J>
	access_flags:      0x0001 [public]
	attribute_count:   2

	Method Attribute #1 - Code:

max_stack: 2, max_locals: 4, code_length: 123
exception_table_length: 0, attribute_count: 2

Bytecode:
Offset	Mnemonic	Parameters
0	iload_1
1	lookupswitch	npairs = 2
11	  case 10: pc + 27 = address 28
19	  case 30: pc + 35 = address 36
-	  default: pc + 43 = address 44
28	fload_2
29	ldc		#30 (float: 2.000000e+01)
31	fadd
32	fstore_2
33	goto		44 (+11)
36	fload_2
37	ldc		#30 (float: 2.000000e+01)
39	fsub
40	fstore_2
41	goto		44 (+3)
44	iload_3
45	tableswitch	low = 2, high = 5
59	  case 2: pc + 31 = address 76
63	  case 3: pc + 40 = address 85
67	  case 4: pc + 49 = address 94
71	  case 5: pc + 58 = address 103
-	  default: pc + 67 = address 112
76	iload_1
77	i2f
78	fload_2
79	fadd
80	f2i
81	istore_1
82	goto		120 (+38)
85	iload_1
86	i2f
87	fload_2
88	fsub
89	f2i
90	istore_1
91	goto		120 (+29)
94	iload_1
95	i2f
96	fload_2
97	fmul
98	f2i
99	istore_1
100	goto		120 (+20)
103	iload_1
104	i2f
105	fload_2
106	fdiv
107	f2i
108	istore_1
109	goto		120 (+11)
112	new		#31 (class: java/lang/Error)
115	dup
116	invokespecial	#32 <Method java/lang/Error.<init>, descriptor: ()V>
119	athrow
120	iload_1
121	i2l
122	lreturn

Code Attribute #1 - LineNumberTable:

line_number_table_length: 10

Table:	index	line_number	start_pc
	1	45		0
	2	46		28
	3	47		36
	4	52		44
	5	53		76
	6	54		85
	7	55		94
	8	56		103
	9	58		112
	10	60		120

Code Attribute #2 - StackMapTable:
Attribute not implemented and ignored.


	Method Attribute #2 - Exceptions:

number_of_exceptions: 1

Exception #1: #31 <java/lang/Error>


Method #4:

	name_index:        #76 <main>
	descriptor_index:  #77 <([Ljava/lang/String;)V>
	access_flags:      0x0009 [public, static]
	attribute_count:   1

	Method Attribute #1 - Code:

max_stack: 2, max_locals: 6, code_length: 49
exception_table_length: 1, attribute_count: 2

Bytecode:
Offset	Mnemonic	Parameters
0	ldc		#33 (string: "ola")
2	astore_1
3	aload_1
4	instanceof	#34 (class: java/lang/String)
7	ifeq		20 (+13)
10	getstatic	#35 <Field java/lang/System.out, descriptor: Ljava/io/PrintStream;>
13	aload_1
14	checkcast	#34 (class: java/lang/String)
17	invokevirtual	#36 <Method java/io/PrintStream.println, descriptor: (Ljava/lang/String;)V>
20	iconst_2
21	iconst_2
22	multianewarray	#37, dimension 2 (class: [[Ljava/lang/String;)
26	astore_2
27	iconst_0
28	istore_3
29	bipush		62
31	iload_3
32	idiv
33	istore		4
35	goto		48 (+13)
38	astore		5
40	getstatic	#35 <Field java/lang/System.out, descriptor: Ljava/io/PrintStream;>
43	aload		5
45	invokevirtual	#39 <Method java/io/PrintStream.println, descriptor: (Ljava/lang/Object;)V>
48	return

Exception table:
Index	start_pc	end_pc	handler_pc	catch_type
1	27		35	38		38 <java/lang/ArithmeticException>

Code Attribute #1 - LineNumberTable:

line_number_table_length: 10

Table:	index	line_number	start_pc
	1	64		0
	2	66		3
	3	67		10
	4	70		20
	5	74		27
	6	75		29
	7	78		35
	8	76		38
	9	77		40
	10	79		48

Code Attribute #2 - StackMapTable:
Attribute not implemented and ignored.


Method #5:

	name_index:        #81 <<clinit>>
	descriptor_index:  #67 <()V>
	access_flags:      0x0008 [static]
	attribute_count:   1

	Method Attribute #1 - Code:

max_stack: 4, max_locals: 0, code_length: 25
exception_table_length: 0, attribute_count: 1

Bytecode:
Offset	Mnemonic	Parameters
0	iconst_3
1	newarray	10 (array of int)
3	dup
4	iconst_0
5	iconst_1
6	iastore
7	dup
8	iconst_1
9	iconst_2
10	iastore
11	dup
12	iconst_2
13	iconst_3
14	iastore
15	putstatic	#40 <Field examples/LongCode.array_member, descriptor: [I>
18	ldc2_w		#41 (long: 98765432123456789)
21	putstatic	#29 <Field examples/LongCode.static_long_member, descriptor: J>
24	return

Code Attribute #1 - LineNumberTable:

line_number_table_length: 2

Table:	index	line_number	start_pc
	1	7		0
	2	10		18


==== Class Attributes ====

	Attribute #1 - SourceFile:

sourcefile_index: #83 <LongCode.java>


	Attribute #2 - InnerClasses:

number_of_classes: 2

Inner Class #1:

inner_class_info_index:   #26 <examples/LongCode$NestedClass>
outer_class_info_index:   #43 <examples/LongCode>
inner_name_index:         #47 <NestedClass>
inner_class_access_flags: 0x0000 [no flags]

Inner Class #2:

inner_class_info_index:   #49 <examples/LongCode$Test>
outer_class_info_index:   #43 <examples/LongCode>
inner_name_index:         #50 <Test>
inner_class_access_flags: 0x0608 [abstract, static, interface]
